<?xml version="1.0" encoding="windows-1250"?>  <!--mod by='BartussX'-->
<ArrayOfVehicletype>
    
    <!-- Don't set offroadSpeedModif to 0 -->
    
    <!-- FIRE UNITS -->
    <Vehicletype id="ve_firetruck" type="FIRE" bonuses="FIRE=0.3" price="80000" visibility="1" armour="0" maxSpeed="110" acceleration="2" immobilizedBy="NONE" offroadSpeedModif="0.4" trafficSpeedModif="0" teammembersSeats="4" transportSeats="0" upkeep="8000" terrain="road" patrols="false" waterCapacity="10" spawnChance="1" allDrive="false" chaseProficiency="0" unlockOnDuty="-1"/>
    <Vehicletype id="ve_techtruck" type="FIRE" bonuses="TECH=0.3" price="60000" visibility="1" armour="0" maxSpeed="120" acceleration="4" immobilizedBy="NONE" offroadSpeedModif="0.5" trafficSpeedModif="0" teammembersSeats="4" transportSeats="0" upkeep="10000" terrain="road" patrols="false" waterCapacity="2" spawnChance="0.5" allDrive="false" chaseProficiency="0" unlockOnDuty="-1"/>
    <Vehicletype id="ve_firevan" type="FIRE" bonuses="NONE" price="50000" visibility="1" armour="0" maxSpeed="130" acceleration="3" immobilizedBy="NONE" offroadSpeedModif="0.8" trafficSpeedModif="0" teammembersSeats="4" transportSeats="0" upkeep="5000" terrain="road" patrols="false" waterCapacity="1" spawnChance="0.2" allDrive="false" chaseProficiency="0" unlockOnDuty="-1"/>
    <Vehicletype id="ve_fireheli" type="FIRE" bonuses="FIRE=0.75,SEARCH=0.5,TALL=1" price="300000" visibility="1" armour="0" maxSpeed="250" acceleration="10" immobilizedBy="Wind=15" offroadSpeedModif="1" trafficSpeedModif="0" teammembersSeats="2" transportSeats="0" upkeep="30000" terrain="air" patrols="false" waterCapacity="5" spawnChance="0" allDrive="false" chaseProficiency="0" unlockOnDuty="-1"/>
    <Vehicletype id="ve_ladder" type="FIRE" bonuses="TALL=0.4" price="120000" visibility="1" armour="0" maxSpeed="100" acceleration="3" immobilizedBy="NONE" offroadSpeedModif="0.6" trafficSpeedModif="0" teammembersSeats="2" transportSeats="0" upkeep="12000" terrain="road" patrols="false" waterCapacity="2" spawnChance="0" allDrive="false" chaseProficiency="0" unlockOnDuty="-1"/>
    <Vehicletype id="ve_quad" type="FIRE" bonuses="NONE" price="20000" visibility="1" armour="0" maxSpeed="100" acceleration="3" immobilizedBy="Rain=8,Snow=5" offroadSpeedModif="0.8" trafficSpeedModif="0.25" teammembersSeats="2" transportSeats="0" upkeep="2000" terrain="road" patrols="true" waterCapacity="1" spawnChance="0" allDrive="true" chaseProficiency="0" unlockOnDuty="-1"/>
    <Vehicletype id="ve_firetank" type="FIRE" bonuses="FIRE=0.25" price="130000" visibility="1" armour="0" maxSpeed="100" acceleration="2" immobilizedBy="NONE" offroadSpeedModif="0.6" trafficSpeedModif="0" teammembersSeats="2" transportSeats="0" upkeep="7000" terrain="road" patrols="false" waterCapacity="40" spawnChance="0" allDrive="false" chaseProficiency="0" unlockOnDuty="-1"/>
    <Vehicletype id="ve_ladder2" type="FIRE" bonuses="TALL=1" price="150000" visibility="1" armour="0" maxSpeed="110" acceleration="3" immobilizedBy="NONE" offroadSpeedModif="0.6" trafficSpeedModif="0" teammembersSeats="2" transportSeats="0" upkeep="12000" terrain="road" patrols="false" waterCapacity="4" spawnChance="0" allDrive="false" chaseProficiency="0" unlockOnDuty="1" onsiteModel="ve_ladder"/>
	<Vehicletype id="ve_heavytruck" type="FIRE" bonuses="FIRE=0.8" price="100000" visibility="1" armour="0" maxSpeed="100" acceleration="2" immobilizedBy="NONE" offroadSpeedModif="0.4" trafficSpeedModif="0" teammembersSeats="3" transportSeats="0" upkeep="8000" terrain="road" patrols="false" waterCapacity="18" spawnChance="0.3" allDrive="false" chaseProficiency="0" unlockOnDuty="1" onsiteModel="ve_firetruck"/>
	<Vehicletype id="ve_techtruck2" type="FIRE" bonuses="TECH=0.7" price="130000" visibility="1" armour="0" maxSpeed="110" acceleration="3" immobilizedBy="NONE" offroadSpeedModif="0.4" trafficSpeedModif="0" teammembersSeats="3" transportSeats="0" upkeep="10000" terrain="road" patrols="false" waterCapacity="2" spawnChance="0.5" allDrive="false" chaseProficiency="0" unlockOnDuty="1" onsiteModel="ve_techtruck"/>/>
    <Vehicletype id="ve_firetruck2" type="FIRE" bonuses="FIRE=0.6, TECH=0.3" price="145000" visibility="1" armour="0" maxSpeed="120" acceleration="4" immobilizedBy="NONE" offroadSpeedModif="0.5" trafficSpeedModif="0" teammembersSeats="4" transportSeats="0" upkeep="8000" terrain="road" patrols="false" waterCapacity="15" spawnChance="1" allDrive="false" chaseProficiency="0" unlockOnDuty="1" onsiteModel="ve_firetruck"/>/>
    <Vehicletype id="ve_hazmat" type="FIRE" bonuses="TECH=1" price="200000" visibility="1" armour="0" maxSpeed="100" acceleration="2" immobilizedBy="NONE" offroadSpeedModif="0.4" trafficSpeedModif="0" teammembersSeats="3" transportSeats="0" upkeep="10000" terrain="road" patrols="false" waterCapacity="0" spawnChance="0.1" allDrive="false" chaseProficiency="0" unlockOnDuty="1" onsiteModel="ve_techtruck"/>/>
	
	<!-- MEDICAL UNITS -->
    <Vehicletype id="ve_medvan" type="MEDICAL" bonuses="INJURED=0.5" price="50000" visibility="1" armour="0" maxSpeed="120" acceleration="2" immobilizedBy="NONE" offroadSpeedModif="0.25" trafficSpeedModif="0" teammembersSeats="3" transportSeats="2" upkeep="5000" terrain="road" patrols="false" spawnChance="1" allDrive="false" chaseProficiency="0" unlockOnDuty="-1"/>
    <Vehicletype id="ve_medtrans" type="MEDICAL" bonuses="NONE" price="60000" visibility="1" armour="0" maxSpeed="120" acceleration="2" immobilizedBy="NONE" offroadSpeedModif="0.25" trafficSpeedModif="0" teammembersSeats="3" transportSeats="3" upkeep="5000" terrain="road" patrols="false" spawnChance="0.5" allDrive="false" chaseProficiency="0" unlockOnDuty="-1"/>
    <Vehicletype id="ve_medheli" type="MEDICAL" bonuses="SEARCH=0.5" price="300000" visibility="1" armour="0" maxSpeed="250" acceleration="9" immobilizedBy="Wind=15" offroadSpeedModif="0.25" trafficSpeedModif="0" teammembersSeats="2" transportSeats="1" upkeep="30000" terrain="air" patrols="false" spawnChance="0" allDrive="false" chaseProficiency="0" unlockOnDuty="-1"/>
    <Vehicletype id="ve_medcar" type="MEDICAL" bonuses="NONE" price="80000" visibility="1" armour="0" maxSpeed="150" acceleration="4" immobilizedBy="NONE" offroadSpeedModif="0.25" trafficSpeedModif="0" teammembersSeats="2" transportSeats="1" upkeep="8000" terrain="road" patrols="false" spawnChance="0" allDrive="false" chaseProficiency="0" unlockOnDuty="-1"/>
    <Vehicletype id="ve_medbike" type="MEDICAL" bonuses="NONE" price="20000" visibility="1" armour="0" maxSpeed="190" acceleration="7" immobilizedBy="Rain=7,Snow=5" offroadSpeedModif="0.25" trafficSpeedModif="0.5" teammembersSeats="2" transportSeats="0" upkeep="2000" terrain="road" patrols="false" spawnChance="0" allDrive="true" chaseProficiency="0" unlockOnDuty="-1"/>
    <Vehicletype id="ve_medmdn" type="MEDICAL" bonuses="INJURED=1" price="140000" visibility="1" armour="0" maxSpeed="120" acceleration="2" immobilizedBy="NONE" offroadSpeedModif="0.45" trafficSpeedModif="0" teammembersSeats="3" transportSeats="2" upkeep="5000" terrain="road" patrols="false" spawnChance="0" allDrive="false" chaseProficiency="0" unlockOnDuty="1" onsiteModel="ve_medvan"/>

    <!-- POLICE UNITS -->
    <Vehicletype id="ve_polbike" type="POLICE" bonuses="NONE" price="20000" visibility="1" armour="0" maxSpeed="180" acceleration="5" immobilizedBy="Rain=7,Snow=5" offroadSpeedModif="0.25" trafficSpeedModif="0.5" teammembersSeats="2" transportSeats="0" upkeep="2000" terrain="road" patrols="true" spawnChance="0" allDrive="true" chaseProficiency="20" unlockOnDuty="-1"/>
    <Vehicletype id="ve_polcar" type="POLICE" bonuses="NONE" price="50000" visibility="1" armour="0.2" maxSpeed="150" acceleration="5" immobilizedBy="NONE" offroadSpeedModif="0.25" trafficSpeedModif="0" teammembersSeats="2" transportSeats="2" upkeep="5000" terrain="road" patrols="true" spawnChance="1" allDrive="false" chaseProficiency="15" unlockOnDuty="-1"/>
	<Vehicletype id="ve_polvan" type="POLICE" bonuses="NONE" price="80000" visibility="1" armour="0.4" maxSpeed="120" acceleration="4" immobilizedBy="NONE" offroadSpeedModif="0.25" trafficSpeedModif="0" teammembersSeats="4" transportSeats="4" upkeep="8000" terrain="road" patrols="true" spawnChance="1" allDrive="false" chaseProficiency="13" unlockOnDuty="-1"/>
    <Vehicletype id="ve_polheli" type="POLICE" bonuses="SEARCH=1" price="200000" visibility="1" armour="0.3" maxSpeed="260" acceleration="10" immobilizedBy="Wind=15" offroadSpeedModif="1" trafficSpeedModif="0" teammembersSeats="2" transportSeats="0" upkeep="20000" terrain="air" patrols="false" spawnChance="0" allDrive="false" chaseProficiency="0" unlockOnDuty="-1"/>
    <Vehicletype id="ve_bicycle" type="POLICE" bonuses="SEARCH=0.5" price="3500" visibility="1" armour="0" maxSpeed="45" acceleration="20" immobilizedBy="Rain=7,Snow=5" offroadSpeedModif="1" trafficSpeedModif="1" teammembersSeats="2" transportSeats="0" upkeep="500" terrain="offroad" patrols="true" spawnChance="0" allDrive="true" chaseProficiency="10" unlockOnDuty="-1"/>
    <Vehicletype id="ve_unmarked" type="POLICE" bonuses="NONE" price="75000" visibility="0" armour="0.2" maxSpeed="180" acceleration="5" immobilizedBy="NONE" offroadSpeedModif="0.25" trafficSpeedModif="0" teammembersSeats="2" transportSeats="2" upkeep="7500" terrain="road" patrols="true" spawnChance="0" allDrive="false" chaseProficiency="15" unlockOnDuty="-1"/>
    <Vehicletype id="ve_speedcar" type="POLICE" bonuses="NONE" price="180000" visibility="1" armour="0.2" maxSpeed="300" acceleration="10" immobilizedBy="NONE" offroadSpeedModif="0.25" trafficSpeedModif="0" teammembersSeats="2" transportSeats="0" upkeep="18000" terrain="road" patrols="true" spawnChance="0" allDrive="false" chaseProficiency="20" unlockOnDuty="-1"/>
    <Vehicletype id="ve_swatvan" type="POLICE" bonuses="NONE" price="150000" visibility="1" armour="0.9" maxSpeed="110" acceleration="4" immobilizedBy="NONE" offroadSpeedModif="0.25" trafficSpeedModif="0" teammembersSeats="4" transportSeats="4" upkeep="20000" terrain="road" patrols="true" spawnChance="0" allDrive="false" chaseProficiency="13" unlockOnDuty="-1"/>
    <Vehicletype id="ve_polhelibig" type="POLICE" bonuses="SEARCH=1" price="350000" visibility="1" armour="0.3" maxSpeed="230" acceleration="10" immobilizedBy="Wind=15" offroadSpeedModif="1" trafficSpeedModif="0" teammembersSeats="3" transportSeats="2" upkeep="35000" terrain="air" patrols="false" spawnChance="0" allDrive="false" chaseProficiency="0" unlockOnDuty="-1"/>
    <Vehicletype id="ve_horse" type="POLICE" bonuses="SEARCH=0.5" price="12000" visibility="1" armour="0" maxSpeed="55" acceleration="20" immobilizedBy="Rain=7,Snow=5" offroadSpeedModif="1" trafficSpeedModif="1" teammembersSeats="2" transportSeats="0" upkeep="1500" terrain="road" patrols="true" spawnChance="0" allDrive="true" chaseProficiency="10" unlockOnDuty="-1"/>
    <Vehicletype id="ve_polpickup" type="POLICE" bonuses="SEARCH=0.25" price="70000" visibility="1" armour="0.1" maxSpeed="130" acceleration="3" immobilizedBy="NONE" offroadSpeedModif="1" trafficSpeedModif="0" teammembersSeats="2" transportSeats="2" upkeep="5000" terrain="road" patrols="true" spawnChance="0.1" allDrive="false" chaseProficiency="13" unlockOnDuty="-1"/>
    <Vehicletype id="ve_polcannon" type="POLICE" bonuses="FIRE=0.25" price="70000" visibility="1" armour="0.3" maxSpeed="100" acceleration="2" immobilizedBy="NONE" offroadSpeedModif="0.25" trafficSpeedModif="0" teammembersSeats="4" transportSeats="0" upkeep="7000" terrain="road" patrols="false" spawnChance="0" allDrive="false" chaseProficiency="10" unlockOnDuty="-1"/>
    <Vehicletype id="ve_prisonvan" type="POLICE" bonuses="NONE" price="70000" visibility="1" armour="0.0" maxSpeed="120" acceleration="4" immobilizedBy="NONE" offroadSpeedModif="0.25" trafficSpeedModif="0" teammembersSeats="2" transportSeats="6" upkeep="8000" terrain="road" patrols="true" spawnChance="0.25" allDrive="false" chaseProficiency="10" unlockOnDuty="1" onsiteModel="ve_polvan"/>
	<Vehicletype id="ve_polptrl" type="POLICE" bonuses="NONE" price="60000" visibility="1" armour="0.3" maxSpeed="130" acceleration="4" immobilizedBy="NONE" offroadSpeedModif="0.25" trafficSpeedModif="0" teammembersSeats="2" transportSeats="2" upkeep="8000" terrain="road" patrols="true" spawnChance="1" allDrive="false" chaseProficiency="13" unlockOnDuty="1" onsiteModel="ve_polcar"/>
	<Vehicletype id="ve_polcar2" type="POLICE" bonuses="NONE" price="100000" visibility="1" armour="0.5" maxSpeed="135" acceleration="5" immobilizedBy="NONE" offroadSpeedModif="0.3" trafficSpeedModif="0" teammembersSeats="4" transportSeats="4" upkeep="5000" terrain="road" patrols="true" spawnChance="0.25" allDrive="false" chaseProficiency="15" unlockOnDuty="1" onsiteModel="ve_polvan"/>
	<Vehicletype id="ve_polsuv" type="POLICE" bonuses="SEARCH=0.25" price="70000" visibility="1" armour="0.1" maxSpeed="130" acceleration="3" immobilizedBy="NONE" offroadSpeedModif="1" trafficSpeedModif="0" teammembersSeats="2" transportSeats="2" upkeep="5000" terrain="road" patrols="true" spawnChance="0.1" allDrive="false" chaseProficiency="13" unlockOnDuty="1" onsiteModel="ve_polpickup"/>
    <Vehicletype id="ve_polcar3" type="POLICE" bonuses="NONE" price="50000" visibility="1" armour="0.2" maxSpeed="150" acceleration="5" immobilizedBy="NONE" offroadSpeedModif="0.25" trafficSpeedModif="0" teammembersSeats="2" transportSeats="2" upkeep="5000" terrain="road" patrols="true" spawnChance="1" allDrive="false" chaseProficiency="15" unlockOnDuty="1" onsiteModel="ve_polcar"/>
	<Vehicletype id="ve_unmarked2" type="POLICE" bonuses="SEARCH=0.10" price="80000" visibility="0" armour="0.4" maxSpeed="180" acceleration="5" immobilizedBy="NONE" offroadSpeedModif="0.25" trafficSpeedModif="0" teammembersSeats="4" transportSeats="0" upkeep="7500" terrain="road" patrols="true" spawnChance="0" allDrive="false" chaseProficiency="15" unlockOnDuty="1" onsiteModel="ve_polcannon"/>
    <Vehicletype id="ve_onfootpatrol" type="POLICE" bonuses="NONE" price="0" visibility="0" armour="0" maxSpeed="20" acceleration="50" immobilizedBy="NONE" offroadSpeedModif="1" trafficSpeedModif="1" teammembersSeats="2" transportSeats="0" upkeep="500" terrain="offroad" patrols="true" spawnChance="0" allDrive="true" chaseProficiency="10" unlockOnDuty="1" onsiteModel="ve_horse"/>
    <Vehicletype id="ve_unmarkedvan" type="POLICE" bonuses="NONE" price="75000" visibility="0" armour="0.5" maxSpeed="130" acceleration="4" immobilizedBy="NONE" offroadSpeedModif="0.25" trafficSpeedModif="0" teammembersSeats="4" transportSeats="1" upkeep="8000" terrain="road" patrols="true" spawnChance="1" allDrive="false" chaseProficiency="13" unlockOnDuty="1" onsiteModel="ve_polvan"/>
	<Vehicletype id="ve_drone" type="POLICE" bonuses="SEARCH=1" price="10000" visibility="0" armour="0.0" maxSpeed="300" acceleration="200" immobilizedBy="Wind=18" offroadSpeedModif="1" trafficSpeedModif="0" teammembersSeats="1" transportSeats="0" upkeep="20000" terrain="air" patrols="false" spawnChance="0" allDrive="false" chaseProficiency="0" unlockOnDuty="1" onsiteModel="ve_horse"/>
    
	<!-- ARMY UNITS (reinforcements) -->
    <Vehicletype id="ve_armyvan" type="ARMY" bonuses="NONE" price="1000000" visibility="1" armour="1" maxSpeed="120" acceleration="4" immobilizedBy="NONE" offroadSpeedModif="1" trafficSpeedModif="0" teammembersSeats="4" transportSeats="4" upkeep="50000" terrain="road" patrols="true" spawnChance="0" allDrive="false" chaseProficiency="1" unlockOnDuty="-1"/>

    <!-- CIVILIAN UNITS -->
    <Vehicletype id="ve_civil_bicycle" type="CIVILIAN" bonuses="NONE" price="5000" visibility="1" armour="0" maxSpeed="40" acceleration="20" immobilizedBy="Rain=8,Snow=5" offroadSpeedModif="1" trafficSpeedModif="1" teammembersSeats="2" transportSeats="0" upkeep="500" terrain="offroad" patrols="false" spawnChance="0" allDrive="true" chaseProficiency="0"/>
    <Vehicletype id="ve_civil_bike" type="CIVILIAN" bonuses="NONE" price="20000" visibility="1" armour="0" maxSpeed="180" acceleration="50" immobilizedBy="Rain=8,Snow=5" offroadSpeedModif="0.25" trafficSpeedModif="0.5" teammembersSeats="2" transportSeats="0" upkeep="2000" terrain="road" patrols="false" spawnChance="0" allDrive="false" chaseProficiency="0"/>
    <Vehicletype id="ve_civil_car" type="CIVILIAN" bonuses="NONE" price="50000" visibility="1" armour="0" maxSpeed="120" acceleration="30" immobilizedBy="NONE" offroadSpeedModif="0.25" trafficSpeedModif="0" teammembersSeats="2" transportSeats="2" upkeep="5000" terrain="road" patrols="false" spawnChance="0" allDrive="false" chaseProficiency="0"/>
    <Vehicletype id="ve_civil_van" type="CIVILIAN" bonuses="NONE" price="50000" visibility="1" armour="0" maxSpeed="100" acceleration="20" immobilizedBy="NONE" offroadSpeedModif="0.25" trafficSpeedModif="0" teammembersSeats="3" transportSeats="2" upkeep="5000" terrain="road" patrols="false" spawnChance="0" allDrive="false" chaseProficiency="0"/>
    <Vehicletype id="ve_civil_speedcar" type="CIVILIAN" bonuses="NONE" price="180000" visibility="1" armour="0" maxSpeed="250" acceleration="40" immobilizedBy="NONE" offroadSpeedModif="0.25" trafficSpeedModif="0" teammembersSeats="2" transportSeats="0" upkeep="18000" terrain="road" patrols="false" spawnChance="0" allDrive="false" chaseProficiency="0"/>
    <Vehicletype id="ve_civil_walk" type="CIVILIAN" bonuses="NONE" price="0" visibility="1" armour="0" maxSpeed="20" acceleration="40" immobilizedBy="NONE" offroadSpeedModif="1" trafficSpeedModif="1" teammembersSeats="2" transportSeats="0" upkeep="18000" terrain="road" patrols="false" spawnChance="0" allDrive="true" chaseProficiency="0"/>
    <Vehicletype id="ve_civil_finalchase" type="CIVILIAN" bonuses="NONE" price="0" visibility="1" armour="0" maxSpeed="180" acceleration="5" immobilizedBy="NONE" offroadSpeedModif="1" trafficSpeedModif="1" teammembersSeats="2" transportSeats="0" upkeep="18000" terrain="road" patrols="false" spawnChance="0" allDrive="true" chaseProficiency="0"/>
    <Vehicletype id="ve_civil_followed_remastered" type="CIVILIAN" bonuses="NONE" price="0" visibility="1" armour="0" maxSpeed="50" acceleration="200" immobilizedBy="NONE" offroadSpeedModif="1" trafficSpeedModif="1" teammembersSeats="2" transportSeats="0" upkeep="18000" terrain="road" patrols="false" spawnChance="0" allDrive="true" chaseProficiency="0"/>
</ArrayOfVehicletype> 
